set_cell_step/__init__.py
set_cell_step/_version.py
set_cell_step/set_cell.py
set_cell_step/set_cell_parameters.py
set_cell_step/set_cell_step.py
set_cell_step/tk_set_cell.py
set_cell_step/data/references.bib
set_cell_step-2021.10.14.dist-info/AUTHORS.rst
set_cell_step-2021.10.14.dist-info/LICENSE
set_cell_step-2021.10.14.dist-info/METADATA
set_cell_step-2021.10.14.dist-info/WHEEL
set_cell_step-2021.10.14.dist-info/entry_points.txt
set_cell_step-2021.10.14.dist-info/top_level.txt
set_cell_step-2021.10.14.dist-info/zip-safe
set_cell_step-2021.10.14.dist-info/RECORD
