Metadata-Version: 2.1
Name: set-cell-step
Version: 2021.10.14
Summary: A SEAMM plug-in for setting the periodic (unit) cell.
Home-page: https://github.com/molssi-seamm/set_cell_step
Author: Paul Saxe
Author-email: psaxe@molssi.org
License: BSD-3-Clause
Keywords: SEAMM,plug-in,flowchart,unitcell,crystal,atomistic
Platform: Linux
Platform: Mac OS-X
Platform: Unix
Platform: Windows
Classifier: Development Status :: 5 - Production/Stable
Classifier: Topic :: Scientific/Engineering :: Chemistry
Classifier: Topic :: Scientific/Engineering :: Physics
Classifier: License :: OSI Approved :: BSD License
Classifier: Natural Language :: English
Classifier: Programming Language :: Python :: 3 :: Only
Classifier: Programming Language :: Python :: 3.7
Classifier: Programming Language :: Python :: 3.8
License-File: LICENSE
License-File: AUTHORS.rst
Requires-Dist: seamm
